asciju/__init__.py
asciju/asciju.py
asciju/cli.py
asciju-0.1.1.dist-info/AUTHORS.rst
asciju-0.1.1.dist-info/LICENSE
asciju-0.1.1.dist-info/METADATA
asciju-0.1.1.dist-info/WHEEL
asciju-0.1.1.dist-info/entry_points.txt
asciju-0.1.1.dist-info/top_level.txt
asciju-0.1.1.dist-info/RECORD
