Metadata-Version: 2.1
Name: asciju
Version: 0.1.1
Summary: Python package that converts image to ascii
Home-page: https://github.com/aju100/asciju
Author: Aju Tamang
Author-email: ajutamang10@outlook.com
License: MIT license
Keywords: asciju
Platform: UNKNOWN
Classifier: Development Status :: 2 - Pre-Alpha
Classifier: Intended Audience :: Developers
Classifier: License :: OSI Approved :: MIT License
Classifier: Natural Language :: English
Classifier: Programming Language :: Python :: 3
Classifier: Programming Language :: Python :: 3.5
Classifier: Programming Language :: Python :: 3.6
Classifier: Programming Language :: Python :: 3.7
Classifier: Programming Language :: Python :: 3.8
Requires-Python: >=3.5
